odoo9_addon_runbot_relative-9.0.1.0.0-py2.7-nspkg.pth
odoo9_addon_runbot_relative-9.0.1.0.0.dist-info/DESCRIPTION.rst
odoo9_addon_runbot_relative-9.0.1.0.0.dist-info/METADATA
odoo9_addon_runbot_relative-9.0.1.0.0.dist-info/RECORD
odoo9_addon_runbot_relative-9.0.1.0.0.dist-info/WHEEL
odoo9_addon_runbot_relative-9.0.1.0.0.dist-info/metadata.json
odoo9_addon_runbot_relative-9.0.1.0.0.dist-info/namespace_packages.txt
odoo9_addon_runbot_relative-9.0.1.0.0.dist-info/top_level.txt
odoo_addons/runbot_relative/README.rst
odoo_addons/runbot_relative/__init__.py
odoo_addons/runbot_relative/__openerp__.py
odoo_addons/runbot_relative/static/description/icon.png
odoo_addons/runbot_relative/static/src/js/runbot_relative.js
odoo_addons/runbot_relative/views/assets.xml
odoo_addons/runbot_relative/views/runbot_template.xml
